{
  "products": [
    {
      "id": "jko2vslbj4",
      "title": "Scoda",
      "description": "Lorem ipsum dolor sit amet consectetur adipisicing elit. Enim, qui?",
      "price": 600,
      "inCart": false
    },
    {
      "id": "hxgyij8ixgj",
      "title": "Suzuki",
      "description": "Lorem ipsum dolor sit amet consectetur adipisicing elit. Enim, qui?",
      "price": 650,
      "inCart": false
    },
    {
      "id": "tdr6kubr2xd",
      "title": "Tesla",
      "description": "Lorem ipsum dolor sit amet consectetur adipisicing elit. Enim, qui?",
      "price": 700,
      "inCart": false
    },
    {
      "id": "ct4w8vhab5p",
      "title": "Toyota",
      "description": "Lorem ipsum dolor sit amet consectetur adipisicing elit. Enim, qui?",
      "price": 750,
      "inCart": false
    },
    {
      "id": "m7281hc8os",
      "title": "Honda",
      "description": "Lorem ipsum dolor sit amet consectetur adipisicing elit. Enim, qui?",
      "price": 850,
      "inCart": false
    },
    {
      "title": "mazda",
      "price": 43,
      "description": "sdfs",
      "id": "_nsHtHy"
    },
    {
      "title": "OpelAstra",
      "price": 434,
      "description": "adsf",
      "id": "7eTT_ib"
    },
    {
      "title": "Bugatti",
      "price": 33443,
      "description": "sfsfsdfs",
      "id": "H5h1S5S"
    },
    {
      "id": "jko2vslbjdfg4",
      "title": "Scoda",
      "description": "Lorem ipsum dolor sit amet consectetur adipisicing elit. Enim, qui?",
      "price": 600,
      "inCart": false
    },
    {
      "id": "hxgyidfgfj8ixgj",
      "title": "Suzuki",
      "description": "Lorem ipsum dolor sit amet consectetur adipisicing elit. Enim, qui?",
      "price": 650,
      "inCart": false
    },
    {
      "id": "tdr6kfdgubr2xd",
      "title": "Tesla",
      "description": "Lorem ipsum dolor sit amet consectetur adipisicing elit. Enim, qui?",
      "price": 700,
      "inCart": false
    },
    {
      "id": "ct4w8dfgvhab5p",
      "title": "Toyota",
      "description": "Lorem ipsum dolor sit amet consectetur adipisicing elit. Enim, qui?",
      "price": 750,
      "inCart": false
    },
    {
      "id": "m7281hfdgc8os",
      "title": "Honda",
      "description": "Lorem ipsum dolor sit amet consectetur adipisicing elit. Enim, qui?",
      "price": 850,
      "inCart": false
    },
    {
      "title": "mazda",
      "price": 43,
      "description": "sdfs",
      "id": "_nsHtdgfdgHy"
    },
    {
      "title": "OpelAstra",
      "price": 434,
      "description": "adsf",
      "id": "7eTTdfgf_ib"
    },
    {
      "title": "Bugatti",
      "price": 33443,
      "description": "sfsfsdfs",
      "id": "H5h1Sdfgdf5S"
    }
  ],
  "cart": [
    {
      "id": "bix27468fjc",
      "title": "Audi",
      "description": "Lorem ipsum dolor sit amet consectetur adipisicing elit. Enim, qui?",
      "price": 100,
      "quantity": 1
    }
  ]
}